dit_ml/__init__.py
dit_ml/dit.py
dit_ml/rope.py
dit_ml-0.2.10.dist-info/licenses/LICENSE
dit_ml-0.2.10.dist-info/METADATA
dit_ml-0.2.10.dist-info/WHEEL
dit_ml-0.2.10.dist-info/top_level.txt
dit_ml-0.2.10.dist-info/RECORD
