Metadata-Version: 2.4
Name: dit-ml
Version: 0.2.10
Summary: DiT (Diffusion Transformer)
Requires-Python: >=3.10
License-File: LICENSE
Requires-Dist: einops>=0.8.1
Requires-Dist: timm>=1.0.15
Requires-Dist: torch>=2.4.0
Provides-Extra: dev
Requires-Dist: pylint>=3.2.5; extra == "dev"
Requires-Dist: pytest-cov>=5.0.0; extra == "dev"
Requires-Dist: pytest>=8.2.2; extra == "dev"
Dynamic: license-file
